{"restaurants":[{"restaurantId":"7c1013f0-ba5c-4fe6-944c-7b906cd92d0d","restaurantName":"Vũ","phoneNumber":"0275 7986 8965","status":false,"address":"Guaynabo","sets":[{"setId":"1e726436-387c-49b2-8c87-8602b9f6b3c7","description":"Dollar, mission-critical, Checking","setName":"cat"}]},{"restaurantId":"13890d60-d326-44a4-8abf-fcf9a65cdf89","restaurantName":"Phùng","phoneNumber":"0250 6528 7323","status":false,"address":"Green Bay","sets":[{"setId":"963f92e8-ade3-47b0-981e-64867ccec21e","description":"Account, policy, Centers","setName":"dog"}]},{"restaurantId":"871c5544-cf74-468e-b34e-af6296d8f626","restaurantName":"Lê","phoneNumber":"020 9414 5810","status":false,"address":"Rialto","sets":[{"setId":"67ee5e1b-1718-4790-89ec-6dcbba41d2f8","description":"Analyst, repurpose, Principal","setName":"crocodilia"}]},{"restaurantId":"385260c8-e8bb-4291-9f4c-6c73a17814d0","restaurantName":"Trịnh","phoneNumber":"0238 3232 4341","status":true,"address":"Alexandria","sets":[{"setId":"351c69da-41a8-49ce-a77a-e4fbd2a1812c","description":"New, bricks-and-clicks, Paradigm","setName":"cow"}]},{"restaurantId":"6c089b97-d868-4707-bd10-d2f2445819c9","restaurantName":"Đặng","phoneNumber":"0247 2656 8654","status":true,"address":"Carson","sets":[{"setId":"52049b46-d0b8-40b2-9ccb-e92b2b45be94","description":"District, Togo, connecting","setName":"bird"}]},{"restaurantId":"7d4b4755-10b5-4198-abbf-dd53bed0eaf2","restaurantName":"Đinh","phoneNumber":"024 4477 3915","status":false,"address":"Green Bay","sets":[{"setId":"1752be0a-a4e4-4353-966f-a4e74d40789c","description":"Manager, zero, incremental","setName":"cow"}]},{"restaurantId":"a645c222-c75b-42db-9172-da4ccd88646b","restaurantName":"Hoàng","phoneNumber":"0289 4395 8225","status":false,"address":"Hempstead","sets":[{"setId":"1ad41bc1-8d63-42f0-82fe-91647a4a46ca","description":"silver, Identity, Specialist","setName":"lion"}]},{"restaurantId":"b1803eb5-cf53-435f-adb4-dd07278680a3","restaurantName":"Đoàn","phoneNumber":"029 5527 2360","status":false,"address":"Smyrna","sets":[{"setId":"0761276d-abf4-4497-a5b3-1831b8bd0014","description":"Gloves, strategic, mission-critical","setName":"horse"}]},{"restaurantId":"83623862-b8dc-4bf3-a612-7d4cdad888f3","restaurantName":"Hồ","phoneNumber":"025 0786 2839","status":false,"address":"Eagan","sets":[{"setId":"7ec04ee4-2a0b-4257-8b12-5173daa11f1c","description":"Buckinghamshire, web-enabled, Cambridgeshire","setName":"cetacean"}]},{"restaurantId":"e8b567f2-c294-4ac9-b57b-32f666f96cfd","restaurantName":"Đặng","phoneNumber":"023 3283 0363","status":false,"address":"San Juan","sets":[{"setId":"709c59ea-e198-4272-9c71-ef0d1b469ba5","description":"Customizable, magenta, Refined","setName":"crocodilia"}]},{"restaurantId":"a38c9514-29a2-42d1-888e-124724aea6a7","restaurantName":"Mai","phoneNumber":"026 3970 4275","status":false,"address":"Miami Beach","sets":[{"setId":"0ae5272f-d7f0-45d3-9d41-9d315e17cd12","description":"infrastructure, XSS, Loan","setName":"rabbit"}]},{"restaurantId":"b777a70f-11fa-4141-98c8-39a0b4f9cfb7","restaurantName":"Ngô","phoneNumber":"027 1931 2544","status":true,"address":"Springfield","sets":[{"setId":"b639dd5e-c5df-4386-9a70-9b7f8c530eae","description":"Triple-buffered, Avon, parsing","setName":"cow"}]},{"restaurantId":"bacdbbdd-32d4-4317-b470-3ec634b56705","restaurantName":"Dương","phoneNumber":"021 4384 2710","status":false,"address":"Albuquerque","sets":[{"setId":"8d712018-9ad6-4b38-b190-72e87f842c0d","description":"groupware, Books, JBOD","setName":"cow"}]},{"restaurantId":"2cd99f20-d051-414b-a67d-559e1124aadf","restaurantName":"Trương","phoneNumber":"0234 3219 1035","status":true,"address":"Pembroke Pines","sets":[{"setId":"dd623c38-f764-4004-96df-064788c3c02c","description":"SQL, turquoise, Salad","setName":"insect"}]},{"restaurantId":"651d323e-f4e5-48a1-ad3f-5c297042b119","restaurantName":"Lê","phoneNumber":"0230 8833 2658","status":false,"address":"Chino","sets":[{"setId":"b952ce48-9124-48d2-93fc-0829918bba02","description":"schemas, Cambridgeshire, deposit","setName":"rabbit"}]},{"restaurantId":"c1f44066-c7bd-40ea-b049-ff175cc35167","restaurantName":"Ngô","phoneNumber":"022 7080 4040","status":true,"address":"Carolina","sets":[{"setId":"f1eab836-f86b-4b76-b5b7-03d33d52bd26","description":"matrix, application, Minnesota","setName":"bird"}]},{"restaurantId":"3cc7c53f-9851-41b7-97f3-1bbce1dd2775","restaurantName":"Trần","phoneNumber":"0272 3632 7767","status":false,"address":"Burke","sets":[{"setId":"fce26fe0-1bb9-470b-a701-0c12df283c3d","description":"generating, database, white","setName":"cat"}]},{"restaurantId":"4a119c6e-d2cf-4fc4-9444-34d4c1273166","restaurantName":"Trịnh","phoneNumber":"028 9785 7743","status":true,"address":"Austin","sets":[{"setId":"8d8b6c0e-413f-4edf-a467-a930e99cc73a","description":"strategize, multi-byte, experiences","setName":"bird"}]},{"restaurantId":"d884e483-7ada-40c2-af85-26bd6ec8dd77","restaurantName":"Hồ","phoneNumber":"0238 6463 5769","status":false,"address":"Santa Monica","sets":[{"setId":"36bb6e47-99b6-4db1-97bb-3c76e94d8c2a","description":"invoice, incremental, coherent","setName":"crocodilia"}]},{"restaurantId":"96a7f07f-36f3-4c3c-ba3c-233e6aa431ad","restaurantName":"Phan","phoneNumber":"027 4600 6056","status":false,"address":"Pittsburgh","sets":[{"setId":"c81f599f-ef76-4f28-ad05-db1bbeaa3c5e","description":"Refined, copying, generate","setName":"fish"}]},{"restaurantId":"26a1ff1a-59c0-4b29-8185-1198f03009c4","restaurantName":"Lê","phoneNumber":"0223 4863 0910","status":true,"address":"Sarasota","sets":[{"setId":"62d4be41-d4fe-462d-b268-09830bf0b0ed","description":"Tuna, SQL, plum","setName":"bird"}]},{"restaurantId":"cbd6a666-696e-4459-baae-82729aa481e6","restaurantName":"Hồ","phoneNumber":"0233 4190 1985","status":false,"address":"Lancaster","sets":[{"setId":"2c599a3d-5f3b-46b1-99f2-8913687c8a6e","description":"payment, hacking, Director","setName":"insect"}]},{"restaurantId":"cbabbf38-4644-4d62-8257-3cb197893374","restaurantName":"Đinh","phoneNumber":"0257 0016 5931","status":true,"address":"Marysville","sets":[{"setId":"8273b666-cf98-45ed-a6a5-6a46b2812a71","description":"Plastic, generate, redefine","setName":"cetacean"}]},{"restaurantId":"20107b17-9bb7-463f-94e2-49da800971a9","restaurantName":"Đoàn","phoneNumber":"0246 7696 4786","status":true,"address":"Southfield","sets":[{"setId":"9154ca2b-795f-4a9d-9a3a-a75744152436","description":"ability, Strategist, e-enable","setName":"snake"}]},{"restaurantId":"2bb66b06-8e3a-4ed3-969a-fed6465807a1","restaurantName":"Trần","phoneNumber":"0215 9530 6028","status":false,"address":"Trujillo Alto","sets":[{"setId":"e7ae8b5b-9bbc-423c-a56a-9b9e2fc6b7eb","description":"El, Senior, EXE","setName":"bear"}]},{"restaurantId":"5fa90074-43b3-45bf-8b7b-737e6e737eb0","restaurantName":"Đặng","phoneNumber":"027 1528 5374","status":false,"address":"St. Peters","sets":[{"setId":"72eb92b6-065a-453e-8790-6a464a9f0159","description":"Mills, Loan, Fresh","setName":"fish"}]},{"restaurantId":"2a8c3486-2556-43f8-86d0-294d0d4ffff9","restaurantName":"Mai","phoneNumber":"020 3223 1787","status":false,"address":"Encinitas","sets":[{"setId":"450b9e11-77cb-4a21-aa6d-186afc90c10a","description":"Avon, web-enabled, backing","setName":"cetacean"}]},{"restaurantId":"1a688b9f-3597-44dc-b72b-8d96c932b48f","restaurantName":"Dương","phoneNumber":"0225 7544 0676","status":false,"address":"Coral Gables","sets":[{"setId":"9f257ded-5e42-4844-982a-4a17b922f0a0","description":"Oregon, models, Clothing","setName":"rabbit"}]},{"restaurantId":"d43f2f42-7f2a-46e4-9e85-49cc4f9675ea","restaurantName":"Phạm","phoneNumber":"025 8783 3634","status":false,"address":"Citrus Heights","sets":[{"setId":"c733c8db-76fd-4dee-bc7e-528b3cdf0876","description":"Soap, Cambridgeshire, Synergized","setName":"bear"}]},{"restaurantId":"0494c3d2-6ee0-48d1-be61-92898869884e","restaurantName":"Trịnh","phoneNumber":"0241 3451 7190","status":false,"address":"West Valley City","sets":[{"setId":"9b8d40e9-b369-4ae5-92e7-f91ceb4cda36","description":"Practical, management, Account","setName":"dog"}]},{"restaurantId":"f3b52ba3-c187-4d2d-b060-2afd2787b63f","restaurantName":"Trịnh","phoneNumber":"025 4924 4928","status":false,"address":"Pinellas Park","sets":[{"setId":"277a3ede-95ff-4ea2-a172-4a09cb4bae59","description":"Drive, scalable, maximized","setName":"rabbit"}]},{"restaurantId":"5a4f859b-123c-4516-a163-da51aabe298c","restaurantName":"Lê","phoneNumber":"0219 2570 1768","status":false,"address":"Wilmington","sets":[{"setId":"3b0dc8ce-99cb-42ee-8516-77af8c1d3d59","description":"brand, unleash, backing","setName":"snake"}]},{"restaurantId":"599b5fd3-8ba6-421d-b51c-b721eaaae0ab","restaurantName":"Đinh","phoneNumber":"0252 1048 7078","status":true,"address":"Lancaster","sets":[{"setId":"81d5cf1c-6d80-4e34-a36b-b17c88154e8e","description":"Spurs, Consultant, systemic","setName":"dog"}]},{"restaurantId":"554d2618-1824-435e-b7ce-8ffa5b894e18","restaurantName":"Đỗ","phoneNumber":"020 5498 5870","status":false,"address":"Centreville","sets":[{"setId":"02b07e96-978e-4f6f-b415-211130b588a4","description":"interfaces, firewall, out-of-the-box","setName":"snake"}]},{"restaurantId":"8fdc4d9b-3ed2-4cdd-98c9-3439567824a6","restaurantName":"Tô","phoneNumber":"0277 1253 2147","status":true,"address":"Belleville","sets":[{"setId":"263512b1-076d-4128-ae71-aa22a1a7fc53","description":"connect, parsing, interactive","setName":"bear"}]},{"restaurantId":"d1af2b24-15e9-49a5-8d05-8c2a2992abb5","restaurantName":"Hà","phoneNumber":"0284 5272 8668","status":true,"address":"Kissimmee","sets":[{"setId":"613e0752-68a2-4c66-ac43-fedfb963c470","description":"Computers, vortals, yellow","setName":"fish"}]},{"restaurantId":"2650c23f-331a-4a4b-9893-b7a67a0b87d5","restaurantName":"Phùng","phoneNumber":"023 0721 5006","status":true,"address":"Boise City","sets":[{"setId":"c10b243b-9f6e-4f45-841b-bf0fc8337777","description":"TCP, Soft, customer","setName":"insect"}]},{"restaurantId":"1561ad4c-6d6b-40ec-8e44-20f70c16a5e9","restaurantName":"Đinh","phoneNumber":"024 8722 4387","status":false,"address":"Huntington","sets":[{"setId":"a399073c-6cb8-4a21-ad7b-9655f8c3d712","description":"value-added, withdrawal, Riel","setName":"crocodilia"}]},{"restaurantId":"bcf55352-f14c-4dae-a517-e793060ec573","restaurantName":"Đào","phoneNumber":"023 1503 4955","status":false,"address":"Gilroy","sets":[{"setId":"3d7a12b1-6c1a-498e-9010-87bcc58a16a0","description":"synthesizing, Direct, silver","setName":"lion"}]},{"restaurantId":"3e24ec21-db08-4fcc-bcd0-2c584a51d6f2","restaurantName":"Trương","phoneNumber":"0217 8577 2796","status":true,"address":"Owensboro","sets":[{"setId":"2799e2d2-1172-4f32-a23b-0e2c3909e225","description":"Tunnel, Account, Technician","setName":"bird"}]}],"users":[{"id":1,"email":"phamkien3@email.com","password":"123456","name":"phamkien3@email.com"},{"id":2,"email":"phamkien4@email.com","password":"123456","name":"phamkien4@email.com"},{"id":3,"email":"phamkien5@email.com","password":"123456","name":"phamkien5@email.com"},{"id":4,"email":"vulongpt2@email.com","password":"123456","name":"vulongpt2@email.com"},{"id":"4d0a544b-b7a6-436b-9c67-ee3528e49c3a","email":"vulongpt11@email.com","password":"123456","name":"vulongpt11@email.com"},{"id":"75e91a11-b44a-49be-9fc0-0c4ae1dac676","email":"vulongpt12@email.com","password":"123456","name":"vulongpt12@email.com"},{"id":"8a50a84a-4fb3-4208-8281-7f1252d5b1a0","email":"vulongpt13@email.com","password":"123456","name":"vulongpt13@email.com"},{"id":"84ac5a74-cf25-40ac-a1ac-9d6af08c2200","email":"phamkien100@email.com","password":"123456","name":"phamkien100@email.com"},{"id":"9d7c0080-f000-4087-8be2-27e90da84d82","email":"phamkien101@email.com","password":"123456","name":"phamkien101@email.com"}]}